{
	"id": "c23e8ef7-1d92-4d8e-beb5-5dac1fcb6ebb",
	"name": "Bug16environment",
	"values": [
		{
			"key": "url",
			"value": "https://restful-booker.herokuapp.com",
			"type": "default",
			"enabled": true
		},
		{
			"key": "myID",
			"value": "",
			"type": "any",
			"enabled": true
		},
		{
			"key": "AccessData",
			"value": "",
			"type": "any",
			"enabled": true
		}
	],
	"_postman_variable_scope": "environment",
	"_postman_exported_at": "2024-08-26T21:08:05.489Z",
	"_postman_exported_using": "Postman/11.9.1-240820-0942"
}